README.md
setup.cfg
setup.py
medianasms/__init__.py
medianasms/client.py
medianasms/errors.py
medianasms/httpclient.py
medianasms/models.py
medianasms.egg-info/PKG-INFO
medianasms.egg-info/SOURCES.txt
medianasms.egg-info/dependency_links.txt
medianasms.egg-info/requires.txt
medianasms.egg-info/top_level.txt
tests/__init__.py
tests/test_message.py