Metadata-Version: 2.1
Name: medianasms
Version: 1.0.3
Summary: medianasms sdk
Home-page: https://github.com/medianasms/python-rest-sdk
Author: Asghar Dadashzadeh
Author-email: a.dadashzadeh@mediana.ir
License: BSD-2-Clause
Platform: UNKNOWN
Classifier: Programming Language :: Python
Classifier: Programming Language :: Python :: 2
Classifier: Programming Language :: Python :: 3
